p1/__init__.py
p1/array.py
p1/colors.py
p1/jsonfile.py
p1/p1.py
p1/server.py
p1/utils.py
p1/commands/__init__.py
p1/commands/check.py
p1/commands/checkout.py
p1/commands/commit.py
p1/commands/dispatcher.py
p1/commands/help.py
p1/commands/info.py
p1/commands/login.py
p1/commands/logout.py
p1/commands/ls.py
p1/commands/version.py
p1ufcg-0.4.5.dist-info/LICENSE
p1ufcg-0.4.5.dist-info/METADATA
p1ufcg-0.4.5.dist-info/WHEEL
p1ufcg-0.4.5.dist-info/entry_points.txt
p1ufcg-0.4.5.dist-info/top_level.txt
p1ufcg-0.4.5.dist-info/RECORD
