Metadata-Version: 2.1
Name: p1ufcg
Version: 0.4.5
Summary: P1 UFCG
Home-page: http://github.com/daltonserey/p1
Author: Dalton Serey
Author-email: daltonserey@gmail.com
License: MIT
Platform: UNKNOWN
Requires-Python: >=3.8
License-File: LICENSE
Requires-Dist: pyyaml (>=5.4.1)
Requires-Dist: requests (>=2.6.1)
Requires-Dist: cachecontrol[filecache]
Requires-Dist: tst (>=0.18.3)
Requires-Dist: pytest-tst (>=0.1.2)
Requires-Dist: codequery (>=0.1.4)
Requires-Dist: questionary
Requires-Dist: pycodestyle
Requires-Dist: vulture
Requires-Dist: pudb
